Metadata-Version: 2.1
Name: lsplug
Version: 5
Summary: Nicer version of lsusb
Home-page: https://git.sr.ht/~martijnbraam/lsplug
Author: Martijn Braam
Author-email: martijn@brixit.nl
Classifier: License :: OSI Approved :: MIT License
License-File: LICENSE
